{
  "generated_at_utc": "2026-04-05T06:02:58.048081Z",
  "data_excel": "TRABAJOS AIRIA.xlsx",
  "company_corpus_len": 609,
  "limit_per_feed": 3000,
  "max_feed_pages": 15,
  "only_last_days": 2,
  "exclude_deadline_soon_days": 2,
  "feed_entries": 6000,
  "mode": "all",
  "detected_count": 64,
  "rows": [
    {
      "title": "Construcción de dos naves multiusos para actividad deportiva en Ballesteros de Calatrava",
      "summary": "Id licitación: 2026-01-OM; Órgano de Contratación: Junta de Gobierno Local del Ayuntamiento de Ballesteros de Calatrava; Importe: 81994.15 EUR; Estado: PUB",
      "link": "https://contrataciondelestado.es/wps/poc?uri=deeplink:detalle_licitacion&idEvl=BkqJJ61qn%2BJ70UvEyYJSGw%3D%3D",
      "updated": "2026-04-04T10:30:51.995000",
      "publicacion": "2026-04-04T12:28:12",
      "fecha_limite": "",
      "similitud": 0.31379487004011153,
      "bloqueada": false,
      "score": 31.379487004011153,
      "boost_keywords": "",
      "blocked_hits": "",
      "super_keywords": "",
      "priority_cpvs": "",
      "source_feed": "https://contrataciondelsectorpublico.gob.es/sindicacion/sindicacion_643/licitacionesPerfilesContratanteCompleto3.atom",
      "sim": 0.31379487004011153,
      "contract_value_no_vat": "81994.15 EUR"
    },
    {
      "title": "Servicio de asistencia del servicio de laboratorio para seguimiento y control de contratos involucrados en la gestión de la calidad del agua destinada a consumo humano. Años 2026-2028 (Va/Varios). Cap 2 C.P.:90.",
      "summary": "Id licitación: v-03/26-01; Órgano de Contratación: Comité Ejecutivo de la Mancomunidad de los Canales del Taibilla; Importe: 577282.14 EUR; Estado: PRE",
      "link": "https://contrataciondelestado.es/wps/poc?uri=deeplink:detalle_licitacion&idEvl=iyJol%2BiG3JBrSd8H4b2soA%3D%3D",
      "updated": "2026-04-03T18:57:41.571000",
      "publicacion": "2026-04-03T18:57:41.571000",
      "fecha_limite": "",
      "similitud": 0.18561400064059272,
      "bloqueada": false,
      "score": 18.56140006405927,
      "boost_keywords": "",
      "blocked_hits": "",
      "super_keywords": "",
      "priority_cpvs": "",
      "source_feed": "https://contrataciondelsectorpublico.gob.es/sindicacion/sindicacion_643/licitacionesPerfilesContratanteCompleto3.atom",
      "sim": 0.18561400064059272,
      "contract_value_no_vat": "577282.14 EUR"
    },
    {
      "title": "Servicio de consultoría y asistencia jurídica del Consorcio de Residuos Plan Zonal I , Área de Gestión C1 de la Comunitat Valenciana .",
      "summary": "Id licitación: 17/2026; Órgano de Contratación: Junta de Gobierno del Consorcio para la Ejecución de las Previsiones del Plan Zonal de Residuos de la Zona I; Importe: 83057.85 EUR; Estado: PUB",
      "link": "https://contrataciondelestado.es/wps/poc?uri=deeplink:detalle_licitacion&idEvl=uDbEAUt9yImExvMJXBMHHQ%3D%3D",
      "updated": "2026-04-03T09:33:41.256000",
      "publicacion": "2026-04-03T09:13:25",
      "fecha_limite": "",
      "similitud": 0.18510246227630808,
      "bloqueada": false,
      "score": 18.51024622763081,
      "boost_keywords": "",
      "blocked_hits": "",
      "super_keywords": "",
      "priority_cpvs": "",
      "source_feed": "https://contrataciondelsectorpublico.gob.es/sindicacion/sindicacion_643/licitacionesPerfilesContratanteCompleto3.atom",
      "sim": 0.18510246227630808,
      "contract_value_no_vat": "83057.85 EUR"
    },
    {
      "title": "Servicio bancario de pago telemático mediante dispositivos terminales punto de venta (TPV entorno REDSYS), mediante pasarela a través de la página web y sede electrónica.",
      "summary": "Id licitación: 43/pa/ser/26; Órgano de Contratación: Dirección de Suma Gestión Tributaria. Diputación de Alicante; Importe: 631000 EUR; Estado: PUB",
      "link": "https://contrataciondelestado.es/wps/poc?uri=deeplink:detalle_licitacion&idEvl=mswPEN%2FojspLAIVZdUs8KA%3D%3D",
      "updated": "2026-04-03T07:14:35.873000",
      "publicacion": "2026-04-03T09:14:35",
      "fecha_limite": "",
      "similitud": 0.13380485628368885,
      "bloqueada": false,
      "score": 18.380485628368884,
      "boost_keywords": "terminal",
      "blocked_hits": "",
      "super_keywords": "",
      "priority_cpvs": "",
      "source_feed": "https://contrataciondelsectorpublico.gob.es/sindicacion/sindicacion_643/licitacionesPerfilesContratanteCompleto3.atom",
      "sim": 0.13380485628368885,
      "contract_value_no_vat": "631000 EUR"
    },
    {
      "title": "Servicios de prestaciones técnicas y personales para la retransmisión de los actos oficiales con motivo de la visita del Papa León XIV a Canarias 2026",
      "summary": "Id licitación: TVPC_08SAU_AR26; Órgano de Contratación: Televisión Pública de Canarias, S.A.; Importe: 646295.1 EUR; Estado: PUB",
      "link": "https://contrataciondelestado.es/wps/poc?uri=deeplink:detalle_licitacion&idEvl=ZfXN7aIbpzo%2Bk2oCbDosIw%3D%3D",
      "updated": "2026-04-03T07:54:03.298000",
      "publicacion": "2026-04-03T09:11:53",
      "fecha_limite": "",
      "similitud": 0.15295986963472627,
      "bloqueada": false,
      "score": 15.295986963472627,
      "boost_keywords": "",
      "blocked_hits": "",
      "super_keywords": "",
      "priority_cpvs": "",
      "source_feed": "https://contrataciondelsectorpublico.gob.es/sindicacion/sindicacion_643/licitacionesPerfilesContratanteCompleto3.atom",
      "sim": 0.15295986963472627,
      "contract_value_no_vat": "646295.1 EUR"
    },
    {
      "title": "Coordinación de obras para Fábrica de Papel de Seguridad.",
      "summary": "Id licitación: 2025/60160941; Órgano de Contratación: Fábrica Nacional de Moneda y Timbre - Real Casa de la Moneda; Importe: 60000 EUR; Estado: RES",
      "link": "https://contrataciondelestado.es/wps/poc?uri=deeplink:detalle_licitacion&idEvl=beGwu2DZdgGkU02jNGj1Fw%3D%3D",
      "updated": "2026-04-03T07:26:45.927000",
      "publicacion": "2026-04-03T07:26:45.927000",
      "fecha_limite": "",
      "similitud": 0.14917734185820697,
      "bloqueada": false,
      "score": 14.917734185820697,
      "boost_keywords": "",
      "blocked_hits": "",
      "super_keywords": "",
      "priority_cpvs": "",
      "source_feed": "https://contrataciondelsectorpublico.gob.es/sindicacion/sindicacion_643/licitacionesPerfilesContratanteCompleto3.atom",
      "sim": 0.14917734185820697,
      "contract_value_no_vat": "60000 EUR"
    },
    {
      "title": "Concesión demanial para la explotación de la cantina del parque Mayrena de Caravaca de la Cruz",
      "summary": "Id licitación: 1225424D; Órgano de Contratación: Junta de Gobierno del Ayuntamiento de Caravaca de la Cruz; Importe: 0 EUR; Estado: PUB",
      "link": "https://contrataciondelestado.es/wps/poc?uri=deeplink:detalle_licitacion&idEvl=g0MlPbgd0uG9Hd5zqvq9cg%3D%3D",
      "updated": "2026-04-04T08:37:34.391000",
      "publicacion": "2026-04-04T10:35:25",
      "fecha_limite": "",
      "similitud": 0.14878169547921244,
      "bloqueada": false,
      "score": 14.878169547921244,
      "boost_keywords": "",
      "blocked_hits": "",
      "super_keywords": "",
      "priority_cpvs": "",
      "source_feed": "https://contrataciondelsectorpublico.gob.es/sindicacion/sindicacion_643/licitacionesPerfilesContratanteCompleto3.atom",
      "sim": 0.14878169547921244,
      "contract_value_no_vat": "0 EUR"
    },
    {
      "title": "Servicio de mantenimiento de los equipos de electromedicina de los centros asistenciales de ASEPEYO",
      "summary": "Id licitación: CP00040/2026; Órgano de Contratación: Subdirección General Sanitaria de ASEPEYO. Mutua Colaboradora con la Seguridad Social. num. 151; Importe: 60707 EUR; Estado: PUB",
      "link": "https://contrataciondelestado.es/wps/poc?uri=deeplink:detalle_licitacion&idEvl=uVl%2BxLb4k1E7%2B9FIQYNjeQ%3D%3D",
      "updated": "2026-04-03T07:12:14.206000",
      "publicacion": "2026-04-03T09:12:14",
      "fecha_limite": "",
      "similitud": 0.14826222077529716,
      "bloqueada": false,
      "score": 14.826222077529716,
      "boost_keywords": "",
      "blocked_hits": "",
      "super_keywords": "",
      "priority_cpvs": "",
      "source_feed": "https://contrataciondelsectorpublico.gob.es/sindicacion/sindicacion_643/licitacionesPerfilesContratanteCompleto3.atom",
      "sim": 0.14826222077529716,
      "contract_value_no_vat": "60707 EUR"
    },
    {
      "title": "Contrato de servicios para la ejecución del Programa para la Prevención, Detección y Tratamiento del Absentismo Escolar en la ciudad de Valencia.",
      "summary": "Id licitación: 04101/2026/34-SER; Órgano de Contratación: Junta de Gobierno del Ajuntament de València; Importe: 640686.48 EUR; Estado: PUB",
      "link": "https://contrataciondelestado.es/wps/poc?uri=deeplink:detalle_licitacion&idEvl=FT8BFOnPLOtVq4S9zvaQpQ%3D%3D",
      "updated": "2026-04-03T07:14:52.330000",
      "publicacion": "2026-04-03T09:14:52",
      "fecha_limite": "",
      "similitud": 0.1434402483642391,
      "bloqueada": false,
      "score": 14.34402483642391,
      "boost_keywords": "",
      "blocked_hits": "",
      "super_keywords": "",
      "priority_cpvs": "",
      "source_feed": "https://contrataciondelsectorpublico.gob.es/sindicacion/sindicacion_643/licitacionesPerfilesContratanteCompleto3.atom",
      "sim": 0.1434402483642391,
      "contract_value_no_vat": "640686.48 EUR"
    },
    {
      "title": "Servicios de telecomunicaciones mediante acuerdo marco por procedimiento de licitación con negociación para la Junta de Extremadura, sus organismos autónomos y otros entes adheridos",
      "summary": "Id licitación: PRAM/2024/0000166830; Órgano de Contratación: Consejería de Hacienda y Administración Pública; Importe: 96463553.37 EUR; Estado: ADJ",
      "link": "https://contrataciondelestado.es/wps/poc?uri=deeplink:detalle_licitacion&idEvl=xYpVp9TUVse2gkLQ8TeYKA%3D%3D",
      "updated": "2026-04-03T07:13:41.658000",
      "publicacion": "2026-04-03T07:13:41.658000",
      "fecha_limite": "",
      "similitud": 0.1401340146882187,
      "bloqueada": false,
      "score": 14.01340146882187,
      "boost_keywords": "",
      "blocked_hits": "",
      "super_keywords": "",
      "priority_cpvs": "",
      "source_feed": "https://contrataciondelsectorpublico.gob.es/sindicacion/sindicacion_643/licitacionesPerfilesContratanteCompleto3.atom",
      "sim": 0.1401340146882187,
      "contract_value_no_vat": "96463553.37 EUR"
    },
    {
      "title": "Servicio de Mantenimiento y Conservación de Parques Públicos y Zonas Verdes en el municipio de Motril",
      "summary": "Id licitación: SERV/ABR/CONTRATACION2025000016; Órgano de Contratación: Pleno del Ayuntamiento de Motril; Importe: 2836203.54 EUR; Estado: PUB",
      "link": "https://contrataciondelestado.es/wps/poc?uri=deeplink:detalle_licitacion&idEvl=lsqeUX7Naev9pbnDwlaUlg%3D%3D",
      "updated": "2026-04-03T09:31:07.349000",
      "publicacion": "2026-04-03T09:31:07.349000",
      "fecha_limite": "",
      "similitud": 0.13238039364839949,
      "bloqueada": false,
      "score": 13.238039364839949,
      "boost_keywords": "",
      "blocked_hits": "",
      "super_keywords": "",
      "priority_cpvs": "",
      "source_feed": "https://contrataciondelsectorpublico.gob.es/sindicacion/sindicacion_643/licitacionesPerfilesContratanteCompleto3.atom",
      "sim": 0.13238039364839949,
      "contract_value_no_vat": "2836203.54 EUR"
    },
    {
      "title": "Servicio para la gestión de expedientes económicos en Sorolla 2 de la Mancomunidad de los Canales del Taibilla O.A.",
      "summary": "Id licitación: V-02/26-02; Órgano de Contratación: Comité Ejecutivo de la Mancomunidad de los Canales del Taibilla; Importe: 308171.7 EUR; Estado: PRE",
      "link": "https://contrataciondelestado.es/wps/poc?uri=deeplink:detalle_licitacion&idEvl=qptR30pp95h%2FR5QFTlaM4A%3D%3D",
      "updated": "2026-04-03T18:18:27.662000",
      "publicacion": "2026-04-03T18:18:27.662000",
      "fecha_limite": "",
      "similitud": 0.12730507486067097,
      "bloqueada": false,
      "score": 12.730507486067097,
      "boost_keywords": "",
      "blocked_hits": "",
      "super_keywords": "",
      "priority_cpvs": "",
      "source_feed": "https://contrataciondelsectorpublico.gob.es/sindicacion/sindicacion_643/licitacionesPerfilesContratanteCompleto3.atom",
      "sim": 0.12730507486067097,
      "contract_value_no_vat": "308171.7 EUR"
    },
    {
      "title": "Mantenimiento y servicio gestionado de UNIVERSITAS XXI - RRHH",
      "summary": "Id licitación: 2025SE00037; Órgano de Contratación: Rectorado de la Universitat de València; Importe: 1061294.34 EUR; Estado: RES",
      "link": "https://contrataciondelestado.es/wps/poc?uri=deeplink:detalle_licitacion&idEvl=1kT6POcYD86kU02jNGj1Fw%3D%3D",
      "updated": "2026-04-03T07:11:59.305000",
      "publicacion": "2026-04-03T07:11:59.305000",
      "fecha_limite": "",
      "similitud": 0.1253244866892628,
      "bloqueada": false,
      "score": 12.53244866892628,
      "boost_keywords": "",
      "blocked_hits": "",
      "super_keywords": "",
      "priority_cpvs": "",
      "source_feed": "https://contrataciondelsectorpublico.gob.es/sindicacion/sindicacion_643/licitacionesPerfilesContratanteCompleto3.atom",
      "sim": 0.1253244866892628,
      "contract_value_no_vat": "1061294.34 EUR"
    },
    {
      "title": "Reparación y acondicionamiento de los Colegios de Infantil y Primaria",
      "summary": "Id licitación: 55/2026; Órgano de Contratación: Alcaldía del Ayuntamiento de Ágreda; Importe: 16528.92 EUR; Estado: EV",
      "link": "https://contrataciondelestado.es/wps/poc?uri=deeplink:detalle_licitacion&idEvl=aNw%2FWRhMzR436J9Lctlsuw%3D%3D",
      "updated": "2026-04-04T17:55:10.355000",
      "publicacion": "2026-04-04T17:55:10.355000",
      "fecha_limite": "",
      "similitud": 0.12491716167403467,
      "bloqueada": false,
      "score": 12.491716167403467,
      "boost_keywords": "",
      "blocked_hits": "",
      "super_keywords": "",
      "priority_cpvs": "",
      "source_feed": "https://contrataciondelsectorpublico.gob.es/sindicacion/sindicacion_643/licitacionesPerfilesContratanteCompleto3.atom",
      "sim": 0.12491716167403467,
      "contract_value_no_vat": "16528.92 EUR"
    },
    {
      "title": "Servei de jardineria per a la conservació i manteniment de parcs, jardins, marges, arbrat i espais públics de Fornells de la Selva",
      "summary": "Id licitación: X2026000519; Órgano de Contratación: Ajuntament de Fornells de la Selva; Importe: 247288.68 EUR; Estado: EN PLAZO",
      "link": "https://contractaciopublica.cat/ca/detall-publicacio/ee4252cf-58aa-4928-858c-66ba549df1de/300739370",
      "updated": "2026-04-03T14:00:01.688000",
      "publicacion": "2026-04-03T14:00:01.688000",
      "fecha_limite": "",
      "similitud": 0.12451744491423872,
      "bloqueada": false,
      "score": 12.451744491423872,
      "boost_keywords": "",
      "blocked_hits": "",
      "super_keywords": "",
      "priority_cpvs": "",
      "source_feed": "https://contrataciondelsectorpublico.gob.es/sindicacion/sindicacion_1044/PlataformasAgregadasSinMenores.atom",
      "sim": 0.12451744491423872,
      "contract_value_no_vat": "247288.68 EUR"
    },
    {
      "title": "Acuerdo marco para la prestación de los servicios de puesta a disposición de maquinaria con conductor, para la Societat Anònima de Gestió Sagunt Mitjà Propi Municipal S.A",
      "summary": "Id licitación: AMSAG2026-05; Órgano de Contratación: Dirección General Societat Anonima de Gestió Sagunt Mitja Propi Municipal S.A.; Importe: 0 EUR; Estado: PUB",
      "link": "https://contrataciondelestado.es/wps/poc?uri=deeplink:detalle_licitacion&idEvl=JZOHi1H7uU170UvEyYJSGw%3D%3D",
      "updated": "2026-04-03T07:12:26.184000",
      "publicacion": "2026-04-03T09:12:26",
      "fecha_limite": "",
      "similitud": 0.12306806235176168,
      "bloqueada": false,
      "score": 12.306806235176168,
      "boost_keywords": "",
      "blocked_hits": "",
      "super_keywords": "",
      "priority_cpvs": "",
      "source_feed": "https://contrataciondelsectorpublico.gob.es/sindicacion/sindicacion_643/licitacionesPerfilesContratanteCompleto3.atom",
      "sim": 0.12306806235176168,
      "contract_value_no_vat": "0 EUR"
    },
    {
      "title": "El objeto del contrato a licitar es la prestación del servicio integral de recogida y alojamiento de animales abandonados y gestión del albergue municipal de animales domésticos del municipio de Caudete (Albacete).",
      "summary": "Id licitación: 1470020W Servicio recogida animales abandonados; Órgano de Contratación: Alcaldía del Ayuntamiento de Caudete; Importe: 145199.32 EUR; Estado: RES",
      "link": "https://contrataciondelestado.es/wps/poc?uri=deeplink:detalle_licitacion&idEvl=cHp%2FFbPF3ekUqXM96WStVA%3D%3D",
      "updated": "2026-04-03T07:13:19.489000",
      "publicacion": "2026-04-03T07:13:19.489000",
      "fecha_limite": "",
      "similitud": 0.12129767127145527,
      "bloqueada": false,
      "score": 12.129767127145527,
      "boost_keywords": "",
      "blocked_hits": "",
      "super_keywords": "",
      "priority_cpvs": "",
      "source_feed": "https://contrataciondelsectorpublico.gob.es/sindicacion/sindicacion_643/licitacionesPerfilesContratanteCompleto3.atom",
      "sim": 0.12129767127145527,
      "contract_value_no_vat": "145199.32 EUR"
    },
    {
      "title": "Servicios para el funcionamiento de la Piscina Cubierta Municipal de Algemesí",
      "summary": "Id licitación: PODCH09/2025; Órgano de Contratación: Junta de Gobierno del Ayuntamiento de Algemesí; Importe: 1307680.02 EUR; Estado: RES",
      "link": "https://contrataciondelestado.es/wps/poc?uri=deeplink:detalle_licitacion&idEvl=ycx0qU4tdqdrSd8H4b2soA%3D%3D",
      "updated": "2026-04-04T14:56:31.717000",
      "publicacion": "2026-04-04T14:56:31.717000",
      "fecha_limite": "",
      "similitud": 0.11660403691603406,
      "bloqueada": false,
      "score": 11.660403691603406,
      "boost_keywords": "",
      "blocked_hits": "",
      "super_keywords": "",
      "priority_cpvs": "",
      "source_feed": "https://contrataciondelsectorpublico.gob.es/sindicacion/sindicacion_643/licitacionesPerfilesContratanteCompleto3.atom",
      "sim": 0.11660403691603406,
      "contract_value_no_vat": "1307680.02 EUR"
    },
    {
      "title": "Serv. desarrollo, implantación y puesta en marcha Plataforma Inteligente de Destino (PID) Málaga PIDM2024 Proy. financiado por Unión Europea-NextGenerationEU en marco del Plan de Recuperación, Transformación y Resiliencia. (Política Palanca 5, Componente 14, Inversión 2. Proyecto 03, Subproyecto 16, Actuación 2. Expediente: PDT- 020000-2024-149)",
      "summary": "Id licitación: 125/25; Órgano de Contratación: Junta de Gobierno del Ayuntamiento de Málaga; Importe: 2934005.3 EUR; Estado: RES",
      "link": "https://contrataciondelestado.es/wps/poc?uri=deeplink:detalle_licitacion&idEvl=IzItznzCeoozjChw4z%2FXvw%3D%3D",
      "updated": "2026-04-03T07:26:56.287000",
      "publicacion": "2026-04-03T07:26:56.287000",
      "fecha_limite": "",
      "similitud": 0.11471181300795888,
      "bloqueada": false,
      "score": 11.471181300795887,
      "boost_keywords": "",
      "blocked_hits": "",
      "super_keywords": "",
      "priority_cpvs": "",
      "source_feed": "https://contrataciondelsectorpublico.gob.es/sindicacion/sindicacion_643/licitacionesPerfilesContratanteCompleto3.atom",
      "sim": 0.11471181300795888,
      "contract_value_no_vat": "2934005.3 EUR"
    },
    {
      "title": "Servicio de interpretación de lengua de signos",
      "summary": "Id licitación: 2026.01; Ó“rgano de Contratación: Grupo Euskal Irrati Telebista-Director/a General de EITB ; Importe: 435450.69EUR; Estado: EV",
      "link": "https://www.contratacion.euskadi.eus/webkpe00-kpeperfi/es/contenidos/anuncio_contratacion/expjaso690244/es_doc/index.html",
      "updated": "2026-04-03T13:11:22.368000",
      "publicacion": "2026-04-03T13:11:22.368000",
      "fecha_limite": "",
      "similitud": 0.11468576857146404,
      "bloqueada": false,
      "score": 11.468576857146404,
      "boost_keywords": "",
      "blocked_hits": "",
      "super_keywords": "",
      "priority_cpvs": "",
      "source_feed": "https://contrataciondelsectorpublico.gob.es/sindicacion/sindicacion_1044/PlataformasAgregadasSinMenores.atom",
      "sim": 0.11468576857146404,
      "contract_value_no_vat": "435450.69 EUR"
    },
    {
      "title": "Obras de transformación de los espacios exteriores del centro público de educación infantil y primaria en Arrigorriaga",
      "summary": "Id licitación: 632/2026; Ó“rgano de Contratación: Ayuntamiento de Arrigorriaga-Alcalde; Importe: 330288.43EUR; Estado: EV",
      "link": "https://www.contratacion.euskadi.eus/webkpe00-kpeperfi/es/contenidos/anuncio_contratacion/expjaso694361/es_doc/index.html",
      "updated": "2026-04-03T07:11:06.763000",
      "publicacion": "2026-04-03T07:11:06.763000",
      "fecha_limite": "",
      "similitud": 0.11099455943511029,
      "bloqueada": false,
      "score": 11.099455943511028,
      "boost_keywords": "",
      "blocked_hits": "",
      "super_keywords": "",
      "priority_cpvs": "",
      "source_feed": "https://contrataciondelsectorpublico.gob.es/sindicacion/sindicacion_1044/PlataformasAgregadasSinMenores.atom",
      "sim": 0.11099455943511029,
      "contract_value_no_vat": "330288.43 EUR"
    },
    {
      "title": "Concesión del servicio del ciclo integral del agua en el Ayuntamiento de Ponteareas.",
      "summary": "Id licitación: 9488/2024; Órgano de Contratación: Pleno del Ayuntamiento de Ponteareas; Importe: 12500000 EUR; Estado: PUB",
      "link": "https://contrataciondelestado.es/wps/poc?uri=deeplink:detalle_licitacion&idEvl=9RpsnmeCSepVkTabT%2FRM8A%3D%3D",
      "updated": "2026-04-03T19:58:47.412000",
      "publicacion": "2026-04-03T19:58:47.412000",
      "fecha_limite": "",
      "similitud": 0.11035174430934673,
      "bloqueada": false,
      "score": 11.035174430934672,
      "boost_keywords": "",
      "blocked_hits": "",
      "super_keywords": "",
      "priority_cpvs": "",
      "source_feed": "https://contrataciondelsectorpublico.gob.es/sindicacion/sindicacion_643/licitacionesPerfilesContratanteCompleto3.atom",
      "sim": 0.11035174430934673,
      "contract_value_no_vat": "12500000 EUR"
    },
    {
      "title": "Obras de acondicionamiento del camino Capuro y del inicial del camino de les Foies en el termino municipal de Benicarló.",
      "summary": "Id licitación: 1714848J - (37/2025); Órgano de Contratación: Concejal delegado de Contratación, Patrimonio, Secretaria General, Servicios Lingüísticos, Servicios Informáticos, Administración Electrónica, Transparencia, Participación Ciudadana y Atención a la Ciudadanía del Ayuntamiento de Benicarló; Importe: 349243.96 EUR; Estado: EV",
      "link": "https://contrataciondelestado.es/wps/poc?uri=deeplink:detalle_licitacion&idEvl=GC5SMBvQEub10HRJw8TEnQ%3D%3D",
      "updated": "2026-04-03T10:50:45.775000",
      "publicacion": "2026-04-03T10:50:45.775000",
      "fecha_limite": "",
      "similitud": 0.10753700181645898,
      "bloqueada": false,
      "score": 10.753700181645897,
      "boost_keywords": "",
      "blocked_hits": "",
      "super_keywords": "",
      "priority_cpvs": "",
      "source_feed": "https://contrataciondelsectorpublico.gob.es/sindicacion/sindicacion_643/licitacionesPerfilesContratanteCompleto3.atom",
      "sim": 0.10753700181645898,
      "contract_value_no_vat": "349243.96 EUR"
    },
    {
      "title": "Servicio de impresión y personalización de títulos oficiales, suplementos europeos al Título y sus copias digitales(E-Título y el set electrónico) y Títulos propios de la Universidad Miguel Hernández de Elche.",
      "summary": "Id licitación: Primera prórroga 2024_048; Órgano de Contratación: Rectorado de la Universidad Miguel Hernández de Elche; Importe: 82380 EUR; Estado: RES",
      "link": "https://contrataciondelestado.es/wps/poc?uri=deeplink:detalle_licitacion&idEvl=e2kCmmCPIVkIYE3ZiZ%2BxmQ%3D%3D",
      "updated": "2026-04-03T07:13:33.819000",
      "publicacion": "2026-04-03T07:13:33.819000",
      "fecha_limite": "",
      "similitud": 0.1074377507909338,
      "bloqueada": false,
      "score": 10.74377507909338,
      "boost_keywords": "",
      "blocked_hits": "",
      "super_keywords": "",
      "priority_cpvs": "",
      "source_feed": "https://contrataciondelsectorpublico.gob.es/sindicacion/sindicacion_643/licitacionesPerfilesContratanteCompleto3.atom",
      "sim": 0.1074377507909338,
      "contract_value_no_vat": "82380 EUR"
    },
    {
      "title": "Contrato de servicio de telecomunicaciones",
      "summary": "Id licitación: 8350_AB/03.03/2026; Órgano de Contratación: Fundación Navarra para la gestión de servicios sociales públicos; Importe: 53058,60 EUR; Estado: Evaluación",
      "link": "https://hacienda.navarra.es/sicpportal/mtoAnunciosModalidad.aspx?cod=2603041644283B2768D3",
      "updated": "2026-04-03T23:00:09.380000",
      "publicacion": "2026-04-03T23:00:09.380000",
      "fecha_limite": "",
      "similitud": 0.10608821015888298,
      "bloqueada": false,
      "score": 10.608821015888298,
      "boost_keywords": "",
      "blocked_hits": "",
      "super_keywords": "",
      "priority_cpvs": "",
      "source_feed": "https://contrataciondelsectorpublico.gob.es/sindicacion/sindicacion_1044/PlataformasAgregadasSinMenores.atom",
      "sim": 0.10608821015888298,
      "contract_value_no_vat": "53058,60 EUR"
    },
    {
      "title": "Servicios funerarios de carácter social o excepcional",
      "summary": "Id licitación: 110/25; Órgano de Contratación: Junta de Gobierno Local del Ayuntamiento de Alicante; Importe: 90315.72 EUR; Estado: RES",
      "link": "https://contrataciondelestado.es/wps/poc?uri=deeplink:detalle_licitacion&idEvl=mIwLGzddEOydkQsA7ROvsg%3D%3D",
      "updated": "2026-04-03T07:13:06.617000",
      "publicacion": "2026-04-03T07:13:06.617000",
      "fecha_limite": "",
      "similitud": 0.10350325214390178,
      "bloqueada": false,
      "score": 10.350325214390178,
      "boost_keywords": "",
      "blocked_hits": "",
      "super_keywords": "",
      "priority_cpvs": "",
      "source_feed": "https://contrataciondelsectorpublico.gob.es/sindicacion/sindicacion_643/licitacionesPerfilesContratanteCompleto3.atom",
      "sim": 0.10350325214390178,
      "contract_value_no_vat": "90315.72 EUR"
    },
    {
      "title": "Arantzako pilotalekua berritzeko obrak / Obras para la renovación del frontón de Arantza",
      "summary": "Id licitación: 3007_02/2026; Órgano de Contratación: Ayuntamiento de Arantza; Importe: 42615,43 EUR; Estado: En Plazo",
      "link": "https://hacienda.navarra.es/sicpportal/mtoAnunciosModalidad.aspx?cod=260403130148FEC69A0A",
      "updated": "2026-04-03T23:00:30.948000",
      "publicacion": "2026-04-03T23:00:30.948000",
      "fecha_limite": "",
      "similitud": 0.10184335248614854,
      "bloqueada": false,
      "score": 10.184335248614854,
      "boost_keywords": "",
      "blocked_hits": "",
      "super_keywords": "",
      "priority_cpvs": "",
      "source_feed": "https://contrataciondelsectorpublico.gob.es/sindicacion/sindicacion_1044/PlataformasAgregadasSinMenores.atom",
      "sim": 0.10184335248614854,
      "contract_value_no_vat": "42615,43 EUR"
    },
    {
      "title": "Servicio de actividades deportivas del Ayuntamiento de Alegría-Dulantzi",
      "summary": "Id licitación: 223/2026; Ó“rgano de Contratación: Ayuntamiento de Alegria-Dulantzi-Pleno; Importe: 117446.83EUR; Estado: EV",
      "link": "https://www.contratacion.euskadi.eus/webkpe00-kpeperfi/es/contenidos/anuncio_contratacion/expjaso690968/es_doc/index.html",
      "updated": "2026-04-04T07:11:02.790000",
      "publicacion": "2026-04-04T07:11:02.790000",
      "fecha_limite": "",
      "similitud": 0.10000706433594705,
      "bloqueada": false,
      "score": 10.000706433594706,
      "boost_keywords": "",
      "blocked_hits": "",
      "super_keywords": "",
      "priority_cpvs": "",
      "source_feed": "https://contrataciondelsectorpublico.gob.es/sindicacion/sindicacion_1044/PlataformasAgregadasSinMenores.atom",
      "sim": 0.10000706433594705,
      "contract_value_no_vat": "117446.83 EUR"
    },
    {
      "title": "Gestión de tienda de alimentación en Monreal",
      "summary": "Id licitación: 8128_3/2026; Órgano de Contratación: AYUNTAMIENTO DE MONREAL; Importe: 75,60 EUR; Estado: En Plazo",
      "link": "https://hacienda.navarra.es/sicpportal/mtoAnunciosModalidad.aspx?cod=2604011329317894145E",
      "updated": "2026-04-03T23:00:24.782000",
      "publicacion": "2026-04-03T23:00:24.782000",
      "fecha_limite": "",
      "similitud": 0.09877146220955366,
      "bloqueada": false,
      "score": 9.877146220955366,
      "boost_keywords": "",
      "blocked_hits": "",
      "super_keywords": "",
      "priority_cpvs": "",
      "source_feed": "https://contrataciondelsectorpublico.gob.es/sindicacion/sindicacion_1044/PlataformasAgregadasSinMenores.atom",
      "sim": 0.09877146220955366,
      "contract_value_no_vat": "75,60 EUR"
    },
    {
      "title": "Ejecución y desarrollo de la prueba deportiva Almendros y Volcanes.",
      "summary": "Id licitación: 001/2026; Órgano de Contratación: Alcaldía del Ayuntamiento de Santiago del Teide; Importe: 18000 EUR; Estado: ADJ",
      "link": "https://contrataciondelestado.es/wps/poc?uri=deeplink:detalle_licitacion&idEvl=%2BoJ1i3cuuddPpzdqOdhuWg%3D%3D",
      "updated": "2026-04-03T16:12:50.942000",
      "publicacion": "2026-04-03T16:12:50.942000",
      "fecha_limite": "",
      "similitud": 0.09839598372893774,
      "bloqueada": false,
      "score": 9.839598372893773,
      "boost_keywords": "",
      "blocked_hits": "",
      "super_keywords": "",
      "priority_cpvs": "",
      "source_feed": "https://contrataciondelsectorpublico.gob.es/sindicacion/sindicacion_643/licitacionesPerfilesContratanteCompleto3.atom",
      "sim": 0.09839598372893774,
      "contract_value_no_vat": "18000 EUR"
    },
    {
      "title": "Concesión administrativa para la gestión y explotación del establecimiento hostelero municipal Toki-Alai de Arama.",
      "summary": "Id licitación: ARAMA2026/01; Ó“rgano de Contratación: Ayuntamiento de Arama-Pleno; Importe: 100EUR; Estado: PUB",
      "link": "https://www.contratacion.euskadi.eus/webkpe00-kpeperfi/es/contenidos/anuncio_contratacion/expjaso701415/es_doc/index.html",
      "updated": "2026-04-03T21:11:30.744000",
      "publicacion": "2026-04-03T21:11:30.744000",
      "fecha_limite": "",
      "similitud": 0.09583803167187158,
      "bloqueada": false,
      "score": 9.583803167187158,
      "boost_keywords": "",
      "blocked_hits": "",
      "super_keywords": "",
      "priority_cpvs": "",
      "source_feed": "https://contrataciondelsectorpublico.gob.es/sindicacion/sindicacion_1044/PlataformasAgregadasSinMenores.atom",
      "sim": 0.09583803167187158,
      "contract_value_no_vat": "100 EUR"
    },
    {
      "title": "Contratación del seguro de accidentes colectivos del personal al servicio del Excmo. Ayuntamiento de Carboneras",
      "summary": "Id licitación: 352/2026; Órgano de Contratación: Alcaldía del Ayuntamiento de Carboneras; Importe: 11546.73 EUR; Estado: EV",
      "link": "https://contrataciondelestado.es/wps/poc?uri=deeplink:detalle_licitacion&idEvl=HVLnl85JgF5SYrkJkLlFdw%3D%3D",
      "updated": "2026-04-03T09:06:58.610000",
      "publicacion": "2026-04-03T09:06:58.610000",
      "fecha_limite": "",
      "similitud": 0.09577356146616102,
      "bloqueada": false,
      "score": 9.577356146616102,
      "boost_keywords": "",
      "blocked_hits": "",
      "super_keywords": "",
      "priority_cpvs": "",
      "source_feed": "https://contrataciondelsectorpublico.gob.es/sindicacion/sindicacion_643/licitacionesPerfilesContratanteCompleto3.atom",
      "sim": 0.09577356146616102,
      "contract_value_no_vat": "11546.73 EUR"
    },
    {
      "title": "Serveis de Coordinació i Regidoria Audiovisual, Manteniment d’Equips i Instal·lacions Audiovisuals, i suport a la realització d’esdeveniments al Disseny Hub Barcelona.",
      "summary": "Id licitación: 006_250002176; Órgano de Contratación: Institut de Cultura de Barcelona; Importe: 295200.00 EUR; Estado: EN PLAZO",
      "link": "https://contractaciopublica.cat/ca/detall-publicacio/6b62c646-dd58-4e7e-b429-fefae713bf0f/300739688",
      "updated": "2026-04-04T08:00:03.200000",
      "publicacion": "2026-04-04T08:00:03.200000",
      "fecha_limite": "",
      "similitud": 0.09338695798869065,
      "bloqueada": false,
      "score": 9.338695798869065,
      "boost_keywords": "",
      "blocked_hits": "",
      "super_keywords": "",
      "priority_cpvs": "",
      "source_feed": "https://contrataciondelsectorpublico.gob.es/sindicacion/sindicacion_1044/PlataformasAgregadasSinMenores.atom",
      "sim": 0.09338695798869065,
      "contract_value_no_vat": "295200.00 EUR"
    },
    {
      "title": "“Ayuda en el Hogar (SAF). Modalidad Dependencia” del Ayuntamiento de Noia",
      "summary": "Id licitación: 3755/2025; Órgano de Contratación: Alcaldía del Ayuntamiento de Noia; Importe: 1802089.84 EUR; Estado: PUB",
      "link": "https://contrataciondelestado.es/wps/poc?uri=deeplink:detalle_licitacion&idEvl=e4Uevxw%2FFi6TylGzYmBF9Q%3D%3D",
      "updated": "2026-04-03T07:12:05.616000",
      "publicacion": "2026-04-03T07:12:05.616000",
      "fecha_limite": "",
      "similitud": 0.09256491880520099,
      "bloqueada": false,
      "score": 9.256491880520098,
      "boost_keywords": "",
      "blocked_hits": "",
      "super_keywords": "",
      "priority_cpvs": "",
      "source_feed": "https://contrataciondelsectorpublico.gob.es/sindicacion/sindicacion_643/licitacionesPerfilesContratanteCompleto3.atom",
      "sim": 0.09256491880520099,
      "contract_value_no_vat": "1802089.84 EUR"
    },
    {
      "title": "Servizo de creación do aroma institucional do Corpus Christi de Ponteareas",
      "summary": "Id licitación: 2244/2026; Órgano de Contratación: Alcaldía del Ayuntamiento de Ponteareas; Importe: 33000 EUR; Estado: PUB",
      "link": "https://contrataciondelestado.es/wps/poc?uri=deeplink:detalle_licitacion&idEvl=YpEQDdLOeJHmnwcj%2BxbdTg%3D%3D",
      "updated": "2026-04-03T12:10:16.963000",
      "publicacion": "2026-04-03T12:10:16.963000",
      "fecha_limite": "",
      "similitud": 0.08818087773227627,
      "bloqueada": false,
      "score": 8.818087773227628,
      "boost_keywords": "",
      "blocked_hits": "",
      "super_keywords": "",
      "priority_cpvs": "",
      "source_feed": "https://contrataciondelsectorpublico.gob.es/sindicacion/sindicacion_643/licitacionesPerfilesContratanteCompleto3.atom",
      "sim": 0.08818087773227627,
      "contract_value_no_vat": "33000 EUR"
    },
    {
      "title": "Aprofitament de pastures del Comunal de Junyent 2026-2031",
      "summary": "Id licitación: 17/2026; Órgano de Contratación: Ajuntament de les Valls d'Aguilar; Importe: 5000.00 EUR; Estado: EN PLAZO",
      "link": "https://contractaciopublica.cat/ca/detall-publicacio/9b0994b7-a0c1-4ede-bc2d-993fc2d3d4c7/300739696",
      "updated": "2026-04-03T10:00:03.012000",
      "publicacion": "2026-04-03T10:00:03.012000",
      "fecha_limite": "",
      "similitud": 0.08746003032384733,
      "bloqueada": false,
      "score": 8.746003032384733,
      "boost_keywords": "",
      "blocked_hits": "",
      "super_keywords": "",
      "priority_cpvs": "",
      "source_feed": "https://contrataciondelsectorpublico.gob.es/sindicacion/sindicacion_1044/PlataformasAgregadasSinMenores.atom",
      "sim": 0.08746003032384733,
      "contract_value_no_vat": "5000.00 EUR"
    },
    {
      "title": "L'objecte del contracte és el servei de CASAL D’ESTIU MUNICIPAL, d’acord amb les característiques i condicions que figuren en el plec de condicions tècniques. La prestació del servei s’ajustarà a les condicions establertes per ambdós plecs: el plec de clàusules administratives particular (PCAP) i el plec de condicions tècniques (PCT). En el cas que existeixi alguna contradicció entre el contingut d’ambdós plecs, prevaldrà el primer.",
      "summary": "Id licitación: 2026_79; Órgano de Contratación: AJUNTAMENT DE SANTA FE DEL PENEDÈS; Importe: 55804.80 EUR; Estado: EN PLAZO",
      "link": "https://contractaciopublica.cat/ca/detall-publicacio/538fa7e4-9a6b-4d17-b414-ea23553161f1/300739689",
      "updated": "2026-04-03T12:00:01.863000",
      "publicacion": "2026-04-03T12:00:01.863000",
      "fecha_limite": "",
      "similitud": 0.06864846782345821,
      "bloqueada": false,
      "score": 6.864846782345821,
      "boost_keywords": "",
      "blocked_hits": "",
      "super_keywords": "",
      "priority_cpvs": "",
      "source_feed": "https://contrataciondelsectorpublico.gob.es/sindicacion/sindicacion_1044/PlataformasAgregadasSinMenores.atom",
      "sim": 0.06864846782345821,
      "contract_value_no_vat": "55804.80 EUR"
    },
    {
      "title": "La enajenación del aprovechamiento cinegético del Coto BU-10943, cuya titularidad pertenece a la Junta Vecinal de Brizuela con una Superficie Total de 830,46 hectáreas",
      "summary": "Id licitación: 26/2025; Órgano de Contratación: Junta Vecinal de Brizuela; Importe: 19931.04 EUR; Estado: PUB",
      "link": "https://contrataciondelestado.es/wps/poc?uri=deeplink:detalle_licitacion&idEvl=K%2B8%2FmQ2m5WqIzo3LHNPGcQ%3D%3D",
      "updated": "2026-04-03T10:30:48.854000",
      "publicacion": "2026-04-03T10:30:48.854000",
      "fecha_limite": "",
      "similitud": 0.06837123019185624,
      "bloqueada": false,
      "score": 6.837123019185625,
      "boost_keywords": "",
      "blocked_hits": "",
      "super_keywords": "",
      "priority_cpvs": "",
      "source_feed": "https://contrataciondelsectorpublico.gob.es/sindicacion/sindicacion_643/licitacionesPerfilesContratanteCompleto3.atom",
      "sim": 0.06837123019185624,
      "contract_value_no_vat": "19931.04 EUR"
    },
    {
      "title": "Estudio del estado de las instalaciones, prestación del servicio de operación y mantenimiento de los elementos que conforman el sistema operativo del sistema de recogida neumática de R.S.U. implantado en la zona noroeste de Barakaldo; así como el traslado de los residuos recogidos a las plantas de tratamiento",
      "summary": "Id licitación: SM102612.001; Ó“rgano de Contratación: Ayuntamiento de Barakaldo-Alcalde; Importe: 396089.66EUR; Estado: PUB",
      "link": "https://www.contratacion.euskadi.eus/webkpe00-kpeperfi/es/contenidos/anuncio_contratacion/expjaso700450/es_doc/index.html",
      "updated": "2026-04-03T07:11:06.821000",
      "publicacion": "2026-04-03T07:11:06.821000",
      "fecha_limite": "",
      "similitud": 0.24056027070207286,
      "bloqueada": true,
      "score": 4.056027070207286,
      "boost_keywords": "",
      "blocked_hits": "tala",
      "super_keywords": "",
      "priority_cpvs": "",
      "source_feed": "https://contrataciondelsectorpublico.gob.es/sindicacion/sindicacion_1044/PlataformasAgregadasSinMenores.atom",
      "sim": 0.24056027070207286,
      "contract_value_no_vat": "396089.66 EUR"
    },
    {
      "title": "Concurso para la contratación por procedimiento abierto del servicio de comunicaciones para el Ayuntamiento de Mungia, en el ámbito de la telefonía fija y móvil, transmisión de datos entre sedes municipales, acceso a internet de banda ancha y seguridad perimetral, así como la descripción de terminales y adquisición de hardware necesario.",
      "summary": "Id licitación: 2025/147; Ó“rgano de Contratación: Ayuntamiento de Mungia-Alcalde; Importe: 90909.09EUR; Estado: EV",
      "link": "https://www.contratacion.euskadi.eus/webkpe00-kpeperfi/es/contenidos/anuncio_contratacion/expjaso692326/es_doc/index.html",
      "updated": "2026-04-03T17:11:21.420000",
      "publicacion": "2026-04-03T17:11:21.420000",
      "fecha_limite": "",
      "similitud": 0.15805903409685282,
      "bloqueada": true,
      "score": 0.805903409685282,
      "boost_keywords": "terminal",
      "blocked_hits": "Adquisicion",
      "super_keywords": "",
      "priority_cpvs": "",
      "source_feed": "https://contrataciondelsectorpublico.gob.es/sindicacion/sindicacion_1044/PlataformasAgregadasSinMenores.atom",
      "sim": 0.15805903409685282,
      "contract_value_no_vat": "90909.09 EUR"
    },
    {
      "title": "Servicio de auditoría operacional y control de calidad del servicio de limpieza en estaciones, paradas, dependencias técnicas y administrativas, complejos y material móvil de Ferrocarrils de la Generalitat Valenciana (FGV) en las provincias de Alicante y Valencia.",
      "summary": "Id licitación: 25/029; Órgano de Contratación: Gerencia de Ferrocarrils de la Generalitat Valenciana; Importe: 978600 EUR; Estado: RES",
      "link": "https://contrataciondelestado.es/wps/poc?uri=deeplink:detalle_licitacion&idEvl=kH0Dq%2FYufGCP%2Bo96UAV7cQ%3D%3D",
      "updated": "2026-04-03T07:27:14.178000",
      "publicacion": "2026-04-03T07:27:14.178000",
      "fecha_limite": "",
      "similitud": 0.1945829056077424,
      "bloqueada": true,
      "score": -0.5417094392257589,
      "boost_keywords": "",
      "blocked_hits": "limpieza",
      "super_keywords": "",
      "priority_cpvs": "",
      "source_feed": "https://contrataciondelsectorpublico.gob.es/sindicacion/sindicacion_643/licitacionesPerfilesContratanteCompleto3.atom",
      "sim": 0.1945829056077424,
      "contract_value_no_vat": "978600 EUR"
    },
    {
      "title": "Primera prórroga del “Servicio de control y mantenimiento de la calidad del agua de consumo humano y prevención contra la legionela en las instalaciones de la Autoridad Portuaria de Barcelona”. Clave del expediente: 2026I070005. Ref. Servicio de Contratación: 2026-00078, relacionado con el 2024-00018.",
      "summary": "Id licitación: 2026-00078; Órgano de Contratación: Presidencia del Consejo de Administración de la Autoridad Portuaria de Barcelona (PORT DE BARCELONA); Importe: 162000 EUR; Estado: RES",
      "link": "https://contrataciondelestado.es/wps/poc?uri=deeplink:detalle_licitacion&idEvl=1EiAaKgxh55SYrkJkLlFdw%3D%3D",
      "updated": "2026-04-03T07:15:02.839000",
      "publicacion": "2026-04-03T07:15:02.839000",
      "fecha_limite": "",
      "similitud": 0.18019391844547095,
      "bloqueada": true,
      "score": -1.9806081554529058,
      "boost_keywords": "",
      "blocked_hits": "tala",
      "super_keywords": "",
      "priority_cpvs": "",
      "source_feed": "https://contrataciondelsectorpublico.gob.es/sindicacion/sindicacion_643/licitacionesPerfilesContratanteCompleto3.atom",
      "sim": 0.18019391844547095,
      "contract_value_no_vat": "162000 EUR"
    },
    {
      "title": "Servicio de conservación y mantenimiento integral de las instalaciones deportivas de Las Rozas de Madrid",
      "summary": "Id licitación: 33804/2025; Órgano de Contratación: Junta de Gobierno del Ayuntamiento Las Rozas; Importe: 1652892.56 EUR; Estado: RES",
      "link": "https://contrataciondelestado.es/wps/poc?uri=deeplink:detalle_licitacion&idEvl=KAUhFSqIqVGFQ%2FlhRK79lA%3D%3D",
      "updated": "2026-04-03T07:27:25.124000",
      "publicacion": "2026-04-03T07:27:25.124000",
      "fecha_limite": "",
      "similitud": 0.15653351870429333,
      "bloqueada": true,
      "score": -4.346648129570667,
      "boost_keywords": "",
      "blocked_hits": "tala",
      "super_keywords": "",
      "priority_cpvs": "",
      "source_feed": "https://contrataciondelsectorpublico.gob.es/sindicacion/sindicacion_643/licitacionesPerfilesContratanteCompleto3.atom",
      "sim": 0.15653351870429333,
      "contract_value_no_vat": "1652892.56 EUR"
    },
    {
      "title": "Contratación del servicio de comunicaciones en instalaciones industriales y equipos de captación de señal",
      "summary": "Id licitación: 0533/2026; Órgano de Contratación: Consejería Delegada de la Empresa Metropolitana de Abastecimiento y Saneamiento de Aguas de Sevilla S.A. (EMASESA); Importe: 6724802.4 EUR; Estado: PUB",
      "link": "https://contrataciondelestado.es/wps/poc?uri=deeplink:detalle_licitacion&idEvl=MIFJq5ENNgJxseVhcqrkhw%3D%3D",
      "updated": "2026-04-03T08:12:30.167000",
      "publicacion": "2026-04-03T08:12:30.167000",
      "fecha_limite": "",
      "similitud": 0.14837424841735805,
      "bloqueada": true,
      "score": -5.162575158264195,
      "boost_keywords": "",
      "blocked_hits": "tala",
      "super_keywords": "",
      "priority_cpvs": "",
      "source_feed": "https://contrataciondelsectorpublico.gob.es/sindicacion/sindicacion_643/licitacionesPerfilesContratanteCompleto3.atom",
      "sim": 0.14837424841735805,
      "contract_value_no_vat": "6724802.4 EUR"
    },
    {
      "title": "Servicios de jardinería y mantenimiento viario en las potabilizadoras de Lorca, Torrealta, La Pedrera, Campotéjar, Sierra de la Espada, Letur e instalaciones anexas pertenecientes a la Mancomunidad de los Canales del Taibilla. Años 2027-2029 (VARIOS).",
      "summary": "Id licitación: V-02/26-01; Órgano de Contratación: Comité Ejecutivo de la Mancomunidad de los Canales del Taibilla; Importe: 859305.19 EUR; Estado: PRE",
      "link": "https://contrataciondelestado.es/wps/poc?uri=deeplink:detalle_licitacion&idEvl=5pMiADQ0d2aIzo3LHNPGcQ%3D%3D",
      "updated": "2026-04-03T18:51:16.824000",
      "publicacion": "2026-04-03T18:51:16.824000",
      "fecha_limite": "",
      "similitud": 0.1440393237576608,
      "bloqueada": true,
      "score": -5.596067624233921,
      "boost_keywords": "",
      "blocked_hits": "tala",
      "super_keywords": "",
      "priority_cpvs": "",
      "source_feed": "https://contrataciondelsectorpublico.gob.es/sindicacion/sindicacion_643/licitacionesPerfilesContratanteCompleto3.atom",
      "sim": 0.1440393237576608,
      "contract_value_no_vat": "859305.19 EUR"
    },
    {
      "title": "Suministro de equipamiento necesario para actualizar la Red Valenciana de Vigilancia y Control de la Contaminación Atmosférica",
      "summary": "Id licitación: CMAYOR/2025/24Y03/0113; Órgano de Contratación: Vicepresidente Tercero y Conseller de Medio Ambiente, Infraestructuras, Territorio y de la Recuperación; Importe: 1000049.59 EUR; Estado: PUB",
      "link": "https://contrataciondelestado.es/wps/poc?uri=deeplink:detalle_licitacion&idEvl=giBsMzLBRYMzjChw4z%2FXvw%3D%3D",
      "updated": "2026-04-03T07:12:16.074000",
      "publicacion": "2026-04-03T07:12:16.074000",
      "fecha_limite": "",
      "similitud": 0.1423693086653357,
      "bloqueada": true,
      "score": -5.763069133466431,
      "boost_keywords": "",
      "blocked_hits": "suministro",
      "super_keywords": "",
      "priority_cpvs": "",
      "source_feed": "https://contrataciondelsectorpublico.gob.es/sindicacion/sindicacion_643/licitacionesPerfilesContratanteCompleto3.atom",
      "sim": 0.1423693086653357,
      "contract_value_no_vat": "1000049.59 EUR"
    },
    {
      "title": "Contrato de suministro de 775 contenedores de plástico de carga lateral de fracción resto y 200 contenedores metálicos de carga lateral de fracción resto para la empresa RSU, S.A.",
      "summary": "Id licitación: 26/00026; Órgano de Contratación: Consejo de Administración de Residuos Sólidos Urbanos de Castilla La Mancha S.A.; Importe: 1152000 EUR; Estado: PUB",
      "link": "https://contrataciondelestado.es/wps/poc?uri=deeplink:detalle_licitacion&idEvl=kSrSJRBASQAzjChw4z%2FXvw%3D%3D",
      "updated": "2026-04-03T10:24:13.879000",
      "publicacion": "2026-04-03T10:24:13.879000",
      "fecha_limite": "",
      "similitud": 0.13642690437863003,
      "bloqueada": true,
      "score": -6.357309562136997,
      "boost_keywords": "",
      "blocked_hits": "suministro",
      "super_keywords": "",
      "priority_cpvs": "",
      "source_feed": "https://contrataciondelsectorpublico.gob.es/sindicacion/sindicacion_643/licitacionesPerfilesContratanteCompleto3.atom",
      "sim": 0.13642690437863003,
      "contract_value_no_vat": "1152000 EUR"
    },
    {
      "title": "La prestación del Servicio de Limpieza Pública (Espacios de uso público), viaria y de playas del municipio de Bueu,",
      "summary": "Id licitación: 669/2026; Órgano de Contratación: Junta de Gobierno del Ayuntamiento de Bueu; Importe: 338584.48 EUR; Estado: PUB",
      "link": "https://contrataciondelestado.es/wps/poc?uri=deeplink:detalle_licitacion&idEvl=1RDNqM787XCP%2Bo96UAV7cQ%3D%3D",
      "updated": "2026-04-04T08:41:03.634000",
      "publicacion": "2026-04-04T08:41:03.634000",
      "fecha_limite": "",
      "similitud": 0.13560196847421793,
      "bloqueada": true,
      "score": -6.439803152578207,
      "boost_keywords": "",
      "blocked_hits": "limpieza",
      "super_keywords": "",
      "priority_cpvs": "",
      "source_feed": "https://contrataciondelsectorpublico.gob.es/sindicacion/sindicacion_643/licitacionesPerfilesContratanteCompleto3.atom",
      "sim": 0.13560196847421793,
      "contract_value_no_vat": "338584.48 EUR"
    },
    {
      "title": "Adquisición de ecógrafos para el Servicio de Radiodiagnóstico del Hospital Clínico Universitario de Valencia, del Departamento de Salud de Valencia Clínico/Malvarrosa",
      "summary": "Id licitación: 791/2026; Órgano de Contratación: Departamento de Salud de Valencia Clínico. Dirección Económica-Gerencia; Importe: 551600 EUR; Estado: ADJ",
      "link": "https://contrataciondelestado.es/wps/poc?uri=deeplink:detalle_licitacion&idEvl=eC8l7N9%2BJ7OdkQsA7ROvsg%3D%3D",
      "updated": "2026-04-03T07:14:08.328000",
      "publicacion": "2026-04-03T07:14:08.328000",
      "fecha_limite": "",
      "similitud": 0.13463396724076046,
      "bloqueada": true,
      "score": -6.536603275923953,
      "boost_keywords": "",
      "blocked_hits": "Adquisicion",
      "super_keywords": "",
      "priority_cpvs": "",
      "source_feed": "https://contrataciondelsectorpublico.gob.es/sindicacion/sindicacion_643/licitacionesPerfilesContratanteCompleto3.atom",
      "sim": 0.13463396724076046,
      "contract_value_no_vat": "551600 EUR"
    },
    {
      "title": "Suministro de equipos para los servicios de Pediatría, UCI y Radiodiagnóstico del Hospital Universitario de Ceuta",
      "summary": "Id licitación: PA/2025/025/GCE; Órgano de Contratación: Gerencia de Atención Sanitaria del Instituto Nacional de Gestión Sanitaria en Ceuta; Importe: 159671.64 EUR; Estado: ADJ",
      "link": "https://contrataciondelestado.es/wps/poc?uri=deeplink:detalle_licitacion&idEvl=%2FMJHL%2FQQOeImMOlAXxDEjw%3D%3D",
      "updated": "2026-04-04T13:48:51.947000",
      "publicacion": "2026-04-04T13:48:51.947000",
      "fecha_limite": "",
      "similitud": 0.11968307285677139,
      "bloqueada": true,
      "score": -8.03169271432286,
      "boost_keywords": "",
      "blocked_hits": "suministro",
      "super_keywords": "",
      "priority_cpvs": "",
      "source_feed": "https://contrataciondelsectorpublico.gob.es/sindicacion/sindicacion_643/licitacionesPerfilesContratanteCompleto3.atom",
      "sim": 0.11968307285677139,
      "contract_value_no_vat": "159671.64 EUR"
    },
    {
      "title": "Contrato basado en acuerdo marco de la FEMP. Suministro de electricidad en alta y baja tensión",
      "summary": "Id licitación: 5AC26-3617/2025; Órgano de Contratación: Alcaldía del Ayuntamiento de El Sauzal; Importe: 202636.18 EUR; Estado: RES",
      "link": "https://contrataciondelestado.es/wps/poc?uri=deeplink:detalle_licitacion&idEvl=wwQuqcjTyrwl5NjlNci%2BtA%3D%3D",
      "updated": "2026-04-03T19:55:55.659000",
      "publicacion": "2026-04-03T19:55:55.659000",
      "fecha_limite": "",
      "similitud": 0.11577596567009138,
      "bloqueada": true,
      "score": -8.422403432990862,
      "boost_keywords": "",
      "blocked_hits": "suministro",
      "super_keywords": "",
      "priority_cpvs": "",
      "source_feed": "https://contrataciondelsectorpublico.gob.es/sindicacion/sindicacion_643/licitacionesPerfilesContratanteCompleto3.atom",
      "sim": 0.11577596567009138,
      "contract_value_no_vat": "202636.18 EUR"
    },
    {
      "title": "Sistema Dinámico de Adquisición de Servicios de carácter intelectual, en el periodo 2026 – 2030, por importe igual o inferior a 100.000 euros, mediante procedimiento abierto sujeto a regulación armonizada y tramitación ordinaria.",
      "summary": "Id licitación: 9972/2025; Órgano de Contratación: Alcaldía del Ayuntamiento de Guía de Isora; Importe: 230716.87 EUR; Estado: PUB",
      "link": "https://contrataciondelestado.es/wps/poc?uri=deeplink:detalle_licitacion&idEvl=jN44fG4EpsEQyBAnWzHfCg%3D%3D",
      "updated": "2026-04-03T07:26:50.845000",
      "publicacion": "2026-04-03T07:26:50.845000",
      "fecha_limite": "",
      "similitud": 0.11427282081905232,
      "bloqueada": true,
      "score": -8.572717918094767,
      "boost_keywords": "",
      "blocked_hits": "Adquisicion",
      "super_keywords": "",
      "priority_cpvs": "",
      "source_feed": "https://contrataciondelsectorpublico.gob.es/sindicacion/sindicacion_643/licitacionesPerfilesContratanteCompleto3.atom",
      "sim": 0.11427282081905232,
      "contract_value_no_vat": "230716.87 EUR"
    },
    {
      "title": "suministro de gametos de donante (ovocitos), para la unidad de reproducción humana asistida del hospital Universitari I Politècnic La Fe",
      "summary": "Id licitación: 1371/2025; Órgano de Contratación: Departamento de Salud La Fe. Dirección Económica-Gerencia; Importe: 453600 EUR; Estado: RES",
      "link": "https://contrataciondelestado.es/wps/poc?uri=deeplink:detalle_licitacion&idEvl=XBo9HSXlCuVxseVhcqrkhw%3D%3D",
      "updated": "2026-04-03T07:13:00.891000",
      "publicacion": "2026-04-03T07:13:00.891000",
      "fecha_limite": "",
      "similitud": 0.105758474939649,
      "bloqueada": true,
      "score": -9.4241525060351,
      "boost_keywords": "",
      "blocked_hits": "suministro",
      "super_keywords": "",
      "priority_cpvs": "",
      "source_feed": "https://contrataciondelsectorpublico.gob.es/sindicacion/sindicacion_643/licitacionesPerfilesContratanteCompleto3.atom",
      "sim": 0.105758474939649,
      "contract_value_no_vat": "453600 EUR"
    },
    {
      "title": "Suministro de equipos de sobremesa, monitores y accesorios para equipos de uso compartido y condiciones especiales.",
      "summary": "Id licitación: CMAYOR/2025/31Y05/0064/CES; Órgano de Contratación: Conselleria de Economía, Hacienda y Administración Pública; Importe: 861910 EUR; Estado: ADJ",
      "link": "https://contrataciondelestado.es/wps/poc?uri=deeplink:detalle_licitacion&idEvl=AeCC%2FEzCCBMaF6cS8TCh%2FA%3D%3D",
      "updated": "2026-04-03T07:14:13.165000",
      "publicacion": "2026-04-03T07:14:13.165000",
      "fecha_limite": "",
      "similitud": 0.09825544894595648,
      "bloqueada": true,
      "score": -10.174455105404352,
      "boost_keywords": "",
      "blocked_hits": "suministro",
      "super_keywords": "",
      "priority_cpvs": "",
      "source_feed": "https://contrataciondelsectorpublico.gob.es/sindicacion/sindicacion_643/licitacionesPerfilesContratanteCompleto3.atom",
      "sim": 0.09825544894595648,
      "contract_value_no_vat": "861910 EUR"
    },
    {
      "title": "Limpieza y desinfección de Edificios, dependencias municipales, colegios públicos y polideportivo municipal de Massanassa.",
      "summary": "Id licitación: 2083/2026; Órgano de Contratación: Pleno del Ajuntament de Massanassa; Importe: 1731510.06 EUR; Estado: PUB",
      "link": "https://contrataciondelestado.es/wps/poc?uri=deeplink:detalle_licitacion&idEvl=MiE2yazvDkvVGIpKDxgsAQ%3D%3D",
      "updated": "2026-04-03T07:14:56.620000",
      "publicacion": "2026-04-03T07:14:56.620000",
      "fecha_limite": "",
      "similitud": 0.07681593963365384,
      "bloqueada": true,
      "score": -12.318406036634617,
      "boost_keywords": "",
      "blocked_hits": "limpieza",
      "super_keywords": "",
      "priority_cpvs": "",
      "source_feed": "https://contrataciondelsectorpublico.gob.es/sindicacion/sindicacion_643/licitacionesPerfilesContratanteCompleto3.atom",
      "sim": 0.07681593963365384,
      "contract_value_no_vat": "1731510.06 EUR"
    },
    {
      "title": "Suministro suscripciones para Productos Microsoft 2026",
      "summary": "Id licitación: EJIE-2026-050; Ó“rgano de Contratación: EJIE, S.A. - Sociedad Informática del Gobierno Vasco-Director General, Presidente, Vicepresidente del Consejo de Administración o Consejo de Administraci; Importe: 414213.6EUR; Estado: PUB",
      "link": "https://www.contratacion.euskadi.eus/webkpe00-kpeperfi/es/contenidos/anuncio_contratacion/expjaso701023/es_doc/index.html",
      "updated": "2026-04-03T07:11:07.679000",
      "publicacion": "2026-04-03T07:11:07.679000",
      "fecha_limite": "",
      "similitud": 0.04842314478071241,
      "bloqueada": true,
      "score": -15.157685521928759,
      "boost_keywords": "",
      "blocked_hits": "suministro",
      "super_keywords": "",
      "priority_cpvs": "",
      "source_feed": "https://contrataciondelsectorpublico.gob.es/sindicacion/sindicacion_1044/PlataformasAgregadasSinMenores.atom",
      "sim": 0.04842314478071241,
      "contract_value_no_vat": "414213.6 EUR"
    },
    {
      "title": "Suministro suscripciones para Productos Microsoft Educación 2026",
      "summary": "Id licitación: EJIE-2026-022; Ó“rgano de Contratación: EJIE, S.A. - Sociedad Informática del Gobierno Vasco-Director General, Presidente, Vicepresidente del Consejo de Administración o Consejo de Administraci; Importe: 132753.25EUR; Estado: EV",
      "link": "https://www.contratacion.euskadi.eus/webkpe00-kpeperfi/es/contenidos/anuncio_contratacion/expjaso692514/es_doc/index.html",
      "updated": "2026-04-03T19:11:21.285000",
      "publicacion": "2026-04-03T19:11:21.285000",
      "fecha_limite": "",
      "similitud": 0.047393493213201215,
      "bloqueada": true,
      "score": -15.260650678679879,
      "boost_keywords": "",
      "blocked_hits": "suministro",
      "super_keywords": "",
      "priority_cpvs": "",
      "source_feed": "https://contrataciondelsectorpublico.gob.es/sindicacion/sindicacion_1044/PlataformasAgregadasSinMenores.atom",
      "sim": 0.047393493213201215,
      "contract_value_no_vat": "132753.25 EUR"
    },
    {
      "title": "El objeto del contrato será la realización del suministro, instalación y puesta en funcionamiento de dos (2) sistemasradiográficos universales, así como el mantenimiento durante el periodo de garantía (mínimo dos (2) años), con destino a las sedesdel Instituto de Medicina Legal y Ciencias Forenses (IMLCF) en Las Palmas de Gran Canaria y Santa Cruz de Tenerife,",
      "summary": "Id licitación: SUM/2026/0000005330; Órgano de Contratación: Dirección General de Relaciones con la Administración de Justicia; Importe: 252000 EUR; Estado: PUB",
      "link": "https://contrataciondelestado.es/wps/poc?uri=deeplink:detalle_licitacion&idEvl=WBeXDJIRLJDLIx6q1oPaMg%3D%3D",
      "updated": "2026-04-04T08:01:13.734000",
      "publicacion": "2026-04-04T08:01:13.734000",
      "fecha_limite": "",
      "similitud": 0.19905169143039872,
      "bloqueada": true,
      "score": -20.09483085696013,
      "boost_keywords": "",
      "blocked_hits": "suministro, tala",
      "super_keywords": "",
      "priority_cpvs": "",
      "source_feed": "https://contrataciondelsectorpublico.gob.es/sindicacion/sindicacion_643/licitacionesPerfilesContratanteCompleto3.atom",
      "sim": 0.19905169143039872,
      "contract_value_no_vat": "252000 EUR"
    },
    {
      "title": "Suministro de 2 camiones recolectores para la recogida de residuos a través de contenedores de carga lateral alimentados por gas natural comprimido (GNC) para uso de NEMASA, en la modalidad de arrendamiento operativo (“renting”)",
      "summary": "Id licitación: 05-P/2026; Órgano de Contratación: Consejo de Administración de Neteja, Manteniment i Servicis de Mislata S.A.; Importe: 144000 EUR; Estado: PUB",
      "link": "https://contrataciondelestado.es/wps/poc?uri=deeplink:detalle_licitacion&idEvl=yQaNL8tHT%2B7XOjazN1Dw9Q%3D%3D",
      "updated": "2026-04-03T07:14:29.899000",
      "publicacion": "2026-04-03T07:14:29.899000",
      "fecha_limite": "",
      "similitud": 0.17300494455228785,
      "bloqueada": true,
      "score": -22.699505544771217,
      "boost_keywords": "",
      "blocked_hits": "suministro, Rent",
      "super_keywords": "",
      "priority_cpvs": "",
      "source_feed": "https://contrataciondelsectorpublico.gob.es/sindicacion/sindicacion_643/licitacionesPerfilesContratanteCompleto3.atom",
      "sim": 0.17300494455228785,
      "contract_value_no_vat": "144000 EUR"
    },
    {
      "title": "Suministro e instalación de juegos infantiles en el Parque de las Pozas de Braojos de la Sierra",
      "summary": "Id licitación: 31/2026; Órgano de Contratación: Alcaldía del Ayuntamiento de Braojos de la Sierra; Importe: 46419 EUR; Estado: EV",
      "link": "https://contrataciondelestado.es/wps/poc?uri=deeplink:detalle_licitacion&idEvl=JPPpSp3j59hrhBlEHQFSKA%3D%3D",
      "updated": "2026-04-03T15:09:35.810000",
      "publicacion": "2026-04-03T15:09:35.810000",
      "fecha_limite": "",
      "similitud": 0.14487588057754927,
      "bloqueada": true,
      "score": -25.512411942245073,
      "boost_keywords": "",
      "blocked_hits": "suministro, tala",
      "super_keywords": "",
      "priority_cpvs": "",
      "source_feed": "https://contrataciondelsectorpublico.gob.es/sindicacion/sindicacion_643/licitacionesPerfilesContratanteCompleto3.atom",
      "sim": 0.14487588057754927,
      "contract_value_no_vat": "46419 EUR"
    },
    {
      "title": "Suministro e instalación de equipamiento oceanográfico para la renovación y mejora de los sistemas de navegación de los buques oceanográficos Ángeles Alvariño y Ramón Margalef del Instituto Español de Oceanografía la Agencia Estatal Consejo Superior de Investigaciones Científicas.",
      "summary": "Id licitación: LOT24/26; Órgano de Contratación: Secretaría General de la Agencia Estatal Consejo Superior de Investigaciones Científicas; Importe: 1092000 EUR; Estado: PUB",
      "link": "https://contrataciondelestado.es/wps/poc?uri=deeplink:detalle_licitacion&idEvl=ZzpPktBDEn87u6%2B%2FR7DUoA%3D%3D",
      "updated": "2026-04-03T07:27:06.477000",
      "publicacion": "2026-04-03T07:27:06.477000",
      "fecha_limite": "",
      "similitud": 0.13099293302976994,
      "bloqueada": true,
      "score": -26.900706697023004,
      "boost_keywords": "",
      "blocked_hits": "suministro, tala",
      "super_keywords": "",
      "priority_cpvs": "",
      "source_feed": "https://contrataciondelsectorpublico.gob.es/sindicacion/sindicacion_643/licitacionesPerfilesContratanteCompleto3.atom",
      "sim": 0.13099293302976994,
      "contract_value_no_vat": "1092000 EUR"
    },
    {
      "title": "Suministro e instalación de un grupo electrógeno y depósito auxiliar para la Oficina de Extranjería en Murcia",
      "summary": "Id licitación: 2026/1; Órgano de Contratación: Delegación del Gobierno en Murcia; Importe: 33010.6 EUR; Estado: RES",
      "link": "https://contrataciondelestado.es/wps/poc?uri=deeplink:detalle_licitacion&idEvl=Q7Q50Om7ZzVSYrkJkLlFdw%3D%3D",
      "updated": "2026-04-04T09:06:58.617000",
      "publicacion": "2026-04-04T09:06:58.617000",
      "fecha_limite": "",
      "similitud": 0.10449456183467269,
      "bloqueada": true,
      "score": -29.55054381653273,
      "boost_keywords": "",
      "blocked_hits": "suministro, tala",
      "super_keywords": "",
      "priority_cpvs": "",
      "source_feed": "https://contrataciondelsectorpublico.gob.es/sindicacion/sindicacion_643/licitacionesPerfilesContratanteCompleto3.atom",
      "sim": 0.10449456183467269,
      "contract_value_no_vat": "33010.6 EUR"
    },
    {
      "title": "Contratación del suministro de combustible para los vehículos y furgonetas",
      "summary": "Id licitación: 8350_AB/02/2026; Órgano de Contratación: Fundación Navarra para la gestión de servicios sociales públicos; Importe: 31490,94 EUR; Estado: Evaluación",
      "link": "https://hacienda.navarra.es/sicpportal/mtoAnunciosModalidad.aspx?cod=260304171921371CD30A",
      "updated": "2026-04-03T23:00:18.491000",
      "publicacion": "2026-04-03T23:00:18.491000",
      "fecha_limite": "",
      "similitud": 0.09136863923197629,
      "bloqueada": true,
      "score": -30.86313607680237,
      "boost_keywords": "",
      "blocked_hits": "suministro, Veh",
      "super_keywords": "",
      "priority_cpvs": "",
      "source_feed": "https://contrataciondelsectorpublico.gob.es/sindicacion/sindicacion_1044/PlataformasAgregadasSinMenores.atom",
      "sim": 0.09136863923197629,
      "contract_value_no_vat": "31490,94 EUR"
    },
    {
      "title": "Suministro para el arrendamiento con mantenimiento (renting) de cinco (5) vehículos de policía",
      "summary": "Id licitación: EC25-C10-04450; Órgano de Contratación: Presidencia de la Autoridad Portuaria de Valencia; Importe: 264000 EUR; Estado: RES",
      "link": "https://contrataciondelestado.es/wps/poc?uri=deeplink:detalle_licitacion&idEvl=evUud9Ez7lswYTJJ03sHog%3D%3D",
      "updated": "2026-04-03T07:12:47.731000",
      "publicacion": "2026-04-03T07:12:47.731000",
      "fecha_limite": "",
      "similitud": 0.1120033097323133,
      "bloqueada": true,
      "score": -48.79966902676867,
      "boost_keywords": "",
      "blocked_hits": "suministro, Rent, Veh",
      "super_keywords": "",
      "priority_cpvs": "",
      "source_feed": "https://contrataciondelsectorpublico.gob.es/sindicacion/sindicacion_643/licitacionesPerfilesContratanteCompleto3.atom",
      "sim": 0.1120033097323133,
      "contract_value_no_vat": "264000 EUR"
    }
  ]
}